testufirst/__init__.py
testufirst/main.py
testufirst/__system__/imports.py
testufirst/__system__/index.py
testufirst/__system__/modules/jobs.py
testufirst/__system__/sources/clight.json
testufirst/__system__/sources/logo.ico
testufirst-1.1.5.dist-info/METADATA
testufirst-1.1.5.dist-info/WHEEL
testufirst-1.1.5.dist-info/entry_points.txt
testufirst-1.1.5.dist-info/top_level.txt
testufirst-1.1.5.dist-info/RECORD
