Metadata-Version: 2.4
Name: testufirst
Version: 1.1.5
Summary: Test Project 1
Home-page: 
Author: Irakli Gzirishvili
Author-email: gziraklirex@gmail.com
Classifier: Programming Language :: Python :: 3
Classifier: Operating System :: OS Independent
Requires-Dist: clight
Dynamic: author
Dynamic: author-email
Dynamic: classifier
Dynamic: description
Dynamic: description-content-type
Dynamic: requires-dist
Dynamic: summary
